CHANGES.txt
LICENSE.txt
MANIFEST.in
README.txt
setup.py
pysickle/__init__.py
pysickle/pysickle.py
pysickle.egg-info/PKG-INFO
pysickle.egg-info/SOURCES.txt
pysickle.egg-info/dependency_links.txt
pysickle.egg-info/requires.txt
pysickle.egg-info/top_level.txt