Metadata-Version: 1.1
Name: pysickle
Version: 0.1.1
Summary: Remove outlier sequences from multiple sequence alignment
Home-page: https://pypi.python.org/pypi/pysickle/
Author: Janina Mass
Author-email: janina.mass@hhu.de
License: GPLv3
Platform: UNKNOWN
Classifier: Programming Language :: Python :: 2.7
Classifier: Topic :: Scientific/Engineering :: Bio-Informatics
